Counter/Up_counter/design.sv
// Code your design here
`timescale 1ns/1ps;
module up_counter(q,rst,clk);
  output reg [3:0]q;
  input rst,clk;
  
  initial 
    begin
       q = 4'b0000;
    end 
  
  always @(posedge clk)
    begin 
    if(rst)
      q <= 4'd0;
    else
      q<=q+1;
    end
endmodule

Counter/Up_counter/testbench.sv
// Code your testbench here
// or browse Examples
module stimulus;
  reg CLK,RST;
  wire [3:0]Q;
  
  up_counter up(Q,RST,CLK);
  
  initial 
    begin 
      $dumpfile("dump.vcd");
      $dumpvars(0,stimulus);
    end
  
  initial
    begin
      CLK = 1'b0;
      RST = 1'b1;
    end 
  
  always #10 CLK = ~CLK;
  
    
  initial 
    begin 
      
      $monitor ($time, " RST = %b, Q = %b\n", RST, Q);
      #10 RST = 1'b0;
      #305 $finish;
            
    end
endmodule

Counter/Up_counter/dump.vcd
$date
	Sun Jul 26 12:39:56 2026
$end
$version
	Icarus Verilog
$end
$timescale
	1ps
$end
$scope module stimulus $end
$var wire 4 ! Q [3:0] $end
$var reg 1 " CLK $end
$var reg 1 # RST $end
$scope module up $end
$var wire 1 " clk $end
$var wire 1 # rst $end
$var reg 4 $ q [3:0] $end
$upscope $end
$upscope $end
$enddefinitions $end
$comment Show the parameter values. $end
$dumpall
$end
#0
$dumpvars
b0 $
1#
0"
b0 !
$end
#10000
b1 !
b1 $
0#
1"
#20000
0"
#30000
b10 !
b10 $
1"
#40000
0"
#50000
b11 !
b11 $
1"
#60000
0"
#70000
b100 !
b100 $
1"
#80000
0"
#90000
b101 !
b101 $
1"
#100000
0"
#110000
b110 !
b110 $
1"
#120000
0"
#130000
b111 !
b111 $
1"
#140000
0"
#150000
b1000 !
b1000 $
1"
#160000
0"
#170000
b1001 !
b1001 $
1"
#180000
0"
#190000
b1010 !
b1010 $
1"
#200000
0"
#210000
b1011 !
b1011 $
1"
#220000
0"
#230000
b1100 !
b1100 $
1"
#240000
0"
#250000
b1101 !
b1101 $
1"
#260000
0"
#270000
b1110 !
b1110 $
1"
#280000
0"
#290000
b1111 !
b1111 $
1"
#300000
0"
#310000
b0 !
b0 $
1"
