Counter/Up_down_counter/design.sv
// Code your design here
`timescale 1ns/1ps;
module up_down_counter(q,a,rst,clk);
  input rst,clk;
  output reg [3:0]q	;
  output reg [4:0] a;
  initial
    begin 
      q = 4'b0000;
      a = 5'd0;
    end
  
  always @(posedge clk)
    begin 
      if(rst)
        q<=0;
      
      else 
        begin
          a=a+1;
          if(a<=15)
            q<=q+1;
          else if (a>15 && a<=30)
            q<=q-1;
          else a=0;
        end
    end
endmodule

Counter/Up_down_counter/testbench.sv
// Code your testbench here
// or browse Examples
module stimulus;
  reg CLK,RST;
  wire [3:0]Q;
  wire [4:0] A;
  
  up_down_counter count(Q,A,RST,CLK);
  
  initial 
    begin 
      $dumpfile("dump.vcd");
      $dumpvars(0,stimulus);
    end
  
  initial 
    begin 
      CLK = 1'b0;
      RST = 1'b1;
    end
  
  always #10 CLK = ~CLK;
  
  initial 
    begin 
      
      $monitor($time, " A =%d, Q= %d\n",A, Q);
      
      #10 RST = 0;
      
      #650 $finish;
      
    end 
endmodule

Counter/Up_down_counter/dump.vcd
$date
	Sun Jul 26 12:34:06 2026
$end
$version
	Icarus Verilog
$end
$timescale
	1ps
$end
$scope module stimulus $end
$var wire 4 ! Q [3:0] $end
$var wire 5 " A [4:0] $end
$var reg 1 # CLK $end
$var reg 1 $ RST $end
$scope module count $end
$var wire 1 # clk $end
$var wire 1 $ rst $end
$var reg 5 % a [4:0] $end
$var reg 4 & q [3:0] $end
$upscope $end
$upscope $end
$enddefinitions $end
$comment Show the parameter values. $end
$dumpall
$end
#0
$dumpvars
b0 &
b0 %
1$
0#
b0 "
b0 !
$end
#10000
b1 !
b1 &
b1 "
b1 %
0$
1#
#20000
0#
#30000
b10 !
b10 &
b10 "
b10 %
1#
#40000
0#
#50000
b11 !
b11 &
b11 "
b11 %
1#
#60000
0#
#70000
b100 !
b100 &
b100 "
b100 %
1#
#80000
0#
#90000
b101 !
b101 &
b101 "
b101 %
1#
#100000
0#
#110000
b110 !
b110 &
b110 "
b110 %
1#
#120000
0#
#130000
b111 !
b111 &
b111 "
b111 %
1#
#140000
0#
#150000
b1000 !
b1000 &
b1000 "
b1000 %
1#
#160000
0#
#170000
b1001 !
b1001 &
b1001 "
b1001 %
1#
#180000
0#
#190000
b1010 !
b1010 &
b1010 "
b1010 %
1#
#200000
0#
#210000
b1011 !
b1011 &
b1011 "
b1011 %
1#
#220000
0#
#230000
b1100 !
b1100 &
b1100 "
b1100 %
1#
#240000
0#
#250000
b1101 !
b1101 &
b1101 "
b1101 %
1#
#260000
0#
#270000
b1110 !
b1110 &
b1110 "
b1110 %
1#
#280000
0#
#290000
b1111 !
b1111 &
b1111 "
b1111 %
1#
#300000
0#
#310000
b1110 !
b1110 &
b10000 "
b10000 %
1#
#320000
0#
#330000
b1101 !
b1101 &
b10001 "
b10001 %
1#
#340000
0#
#350000
b1100 !
b1100 &
b10010 "
b10010 %
1#
#360000
0#
#370000
b1011 !
b1011 &
b10011 "
b10011 %
1#
#380000
0#
#390000
b1010 !
b1010 &
b10100 "
b10100 %
1#
#400000
0#
#410000
b1001 !
b1001 &
b10101 "
b10101 %
1#
#420000
0#
#430000
b1000 !
b1000 &
b10110 "
b10110 %
1#
#440000
0#
#450000
b111 !
b111 &
b10111 "
b10111 %
1#
#460000
0#
#470000
b110 !
b110 &
b11000 "
b11000 %
1#
#480000
0#
#490000
b101 !
b101 &
b11001 "
b11001 %
1#
#500000
0#
#510000
b100 !
b100 &
b11010 "
b11010 %
1#
#520000
0#
#530000
b11 !
b11 &
b11011 "
b11011 %
1#
#540000
0#
#550000
b10 !
b10 &
b11100 "
b11100 %
1#
#560000
0#
#570000
b1 !
b1 &
b11101 "
b11101 %
1#
#580000
0#
#590000
b0 !
b0 &
b11110 "
b11110 %
1#
#600000
0#
#610000
b0 "
b0 %
1#
#620000
0#
#630000
b1 !
b1 &
b1 "
b1 %
1#
#640000
0#
#650000
b10 !
b10 &
b10 "
b10 %
1#
